youngones/__init__.py
youngones/auth.py
youngones/config.yaml
youngones_auth-0.0.7.dist-info/WHEEL
youngones_auth-0.0.7.dist-info/METADATA
youngones_auth-0.0.7.dist-info/RECORD
